{"skeleton":{"hash":"ClREE70bWltRGspQwnnp3oICGd0","spine":"3.6.52","width":561,"height":247,"images":"./images/"},"bones":[{"name":"root"},{"name":"bone19","parent":"root","x":5.47,"y":52.93},{"name":"bone2","parent":"bone19","x":21.74,"y":49.32},{"name":"bone3","parent":"bone19","x":-96.84,"y":104.26},{"name":"bone4","parent":"bone19","x":-126.58,"y":1.01},{"name":"bone5","parent":"bone19","x":172.43,"y":0.19},{"name":"bone6","parent":"bone19","x":112.96,"y":109.22},{"name":"bone17","parent":"bone19","x":-217.56,"y":134.02},{"name":"bone18","parent":"bone19","x":234.76,"y":45.44}],"slots":[{"name":"cg7","bone":"bone4","attachment":"cg7"},{"name":"cg6","bone":"bone5","attachment":"cg6"},{"name":"cg5","bone":"bone6","attachment":"cg5"},{"name":"cg4","bone":"bone18","attachment":"cg4"},{"name":"cg3","bone":"bone17","attachment":"cg3"},{"name":"cg2","bone":"bone3","attachment":"cg2"},{"name":"cg1","bone":"bone2","attachment":"cg1"}],"skins":{"default":{"cg1":{"cg1":{"x":-9.81,"y":0.08,"width":498,"height":66}},"cg2":{"cg2":{"x":0.77,"y":-1.86,"width":131,"height":136}},"cg3":{"cg3":{"x":2.49,"y":-2.62,"width":107,"height":108}},"cg4":{"cg4":{"x":4.16,"y":-0.04,"width":107,"height":108}},"cg5":{"cg5":{"x":0.46,"y":0.18,"width":102,"height":102}},"cg6":{"cg6":{"x":-5.51,"y":2.21,"width":115,"height":120}},"cg7":{"cg7":{"x":-5.5,"y":-2.61,"width":115,"height":120}}}},"animations":{"animation":{"slots":{"cg2":{"color":[{"time":0.1667,"color":"ffffffff"},{"time":0.8667,"color":"ffffff00"}]},"cg3":{"color":[{"time":0,"color":"ffffffff"},{"time":0.1333,"color":"ffffffd3","curve":"stepped"},{"time":0.2333,"color":"ffffffd3"},{"time":0.6667,"color":"ffffff00"}]},"cg4":{"color":[{"time":0.1333,"color":"ffffffff"},{"time":0.8667,"color":"ffffff00"}]},"cg5":{"color":[{"time":0.1333,"color":"ffffffff"},{"time":0.6667,"color":"ffffff00"}]},"cg6":{"color":[{"time":0.1333,"color":"ffffffff"},{"time":0.6667,"color":"ffffff00"}]},"cg7":{"color":[{"time":0.1333,"color":"ffffffff"},{"time":0.6667,"color":"ffffff00"}]}},"bones":{"bone2":{"rotate":[{"time":0,"angle":0,"curve":"stepped"},{"time":0.1333,"angle":0,"curve":"stepped"},{"time":0.4333,"angle":0}],"translate":[{"time":0,"x":0,"y":0,"curve":"stepped"},{"time":0.1333,"x":0,"y":0,"curve":"stepped"},{"time":0.4333,"x":0,"y":0}],"scale":[{"time":0,"x":0,"y":0},{"time":0.1333,"x":1,"y":1},{"time":0.2,"x":1.313,"y":1.313},{"time":0.3,"x":0.9,"y":0.9},{"time":0.4333,"x":1,"y":1}],"shear":[{"time":0,"x":0,"y":0,"curve":"stepped"},{"time":0.1333,"x":0,"y":0,"curve":"stepped"},{"time":0.4333,"x":0,"y":0}]},"bone3":{"rotate":[{"time":0,"angle":0},{"time":0.8667,"angle":-33.4}],"translate":[{"time":0,"x":80.59,"y":-50.54},{"time":0.8667,"x":-77.86,"y":117.48}],"scale":[{"time":0,"x":0,"y":0},{"time":0.1667,"x":1,"y":1},{"time":0.8667,"x":0.349,"y":0.349}],"shear":[{"time":0,"x":0,"y":0}]},"bone4":{"rotate":[{"time":0,"angle":0,"curve":"stepped"},{"time":0.1333,"angle":0},{"time":0.6667,"angle":-102.75}],"translate":[{"time":0,"x":109.2,"y":23.8},{"time":0.1333,"x":0,"y":0},{"time":0.6667,"x":-126,"y":-124.6}],"scale":[{"time":0,"x":0,"y":0},{"time":0.1333,"x":1,"y":1},{"time":0.6667,"x":-0.484,"y":-0.484}],"shear":[{"time":0,"x":0,"y":0,"curve":"stepped"},{"time":0.1333,"x":0,"y":0}]},"bone5":{"rotate":[{"time":0,"angle":0,"curve":"stepped"},{"time":0.1333,"angle":0},{"time":0.6667,"angle":115.32}],"translate":[{"time":0,"x":-146.17,"y":9.97},{"time":0.1333,"x":0,"y":0},{"time":0.6667,"x":134.54,"y":-99.66}],"scale":[{"time":0,"x":0,"y":0},{"time":0.1333,"x":1,"y":1}],"shear":[{"time":0,"x":0,"y":0,"curve":"stepped"},{"time":0.1333,"x":0,"y":0}]},"bone6":{"rotate":[{"time":0,"angle":0,"curve":"stepped"},{"time":0.1333,"angle":0}],"translate":[{"time":0,"x":-68.1,"y":-69.76},{"time":0.1333,"x":0,"y":0},{"time":0.6667,"x":111.29,"y":169.42}],"scale":[{"time":0,"x":0,"y":0},{"time":0.1333,"x":1,"y":1}],"shear":[{"time":0,"x":0,"y":0,"curve":"stepped"},{"time":0.1333,"x":0,"y":0}]},"bone17":{"rotate":[{"time":0,"angle":0}],"translate":[{"time":0,"x":98,"y":-58.8},{"time":0.6667,"x":-88.65,"y":33.22}],"scale":[{"time":0,"x":0,"y":0},{"time":0.1333,"x":1,"y":1,"curve":"stepped"},{"time":0.2333,"x":1,"y":1}],"shear":[{"time":0,"x":0,"y":0}]},"bone18":{"rotate":[{"time":0,"angle":0,"curve":"stepped"},{"time":0.1333,"angle":0,"curve":"stepped"},{"time":0.8667,"angle":0}],"translate":[{"time":0,"x":-182.71,"y":-23.25},{"time":0.1333,"x":0,"y":0},{"time":0.8667,"x":99.66,"y":-21.59}],"scale":[{"time":0,"x":0,"y":0},{"time":0.1333,"x":1,"y":1,"curve":"stepped"},{"time":0.8667,"x":1,"y":1}],"shear":[{"time":0,"x":0,"y":0,"curve":"stepped"},{"time":0.1333,"x":0,"y":0,"curve":"stepped"},{"time":0.8667,"x":0,"y":0}]},"bone19":{"rotate":[{"time":0,"angle":0}],"translate":[{"time":0,"x":0,"y":0}],"scale":[{"time":0,"x":1,"y":1}],"shear":[{"time":0,"x":0,"y":0}]}}}}}